{
  "date": "2026-06-28",
  "generated_at_utc": "2026-06-28 13:22 UTC",
  "picks": [
    {
      "rank": 1,
      "batter_id": "621020",
      "name": "Dansby Swanson",
      "team": "CHC",
      "opp_pitcher": "Brandon Woodruff",
      "opp_team": "MIL",
      "game": "CHC @ MIL",
      "in_lineup": null,
      "lineup_pos": null,
      "line": "1.5",
      "best_edge": 0.032941677265278524,
      "p_over_15": 0.5569416772652785,
      "p_over_25": 0.4781220107963752,
      "p_over_15_raw": 0.8675062480865305,
      "p_over_25_raw": 0.6851205958599605,
      "e_hrr": 3.5324916005145814,
      "expected_pa": 4.15,
      "quality_mult": 1.1376637358490318,
      "hf": 1.016380224880734,
      "park_mult": 1.01,
      "weather_mult": 1.0180374125,
      "bullpen_mult": 0.9876544648855863,
      "bvp_mult": 1.2,
      "bvp_pa": 17,
      "bvt_mult": 1.034109915821948,
      "bvt_pa": 288,
      "bvs_mult": 0.9502871912587171,
      "bvs_pa": 32,
      "impact": 1.0,
      "recent_pa": 53,
      "real_line": 0.5,
      "real_over_price": -154,
      "real_book": "DraftKings",
      "real_p_over": 0.9707680093883843,
      "real_breakeven": 0.6062992125984252,
      "real_edge": 0.364468796789959
    },
    {
      "rank": 2,
      "batter_id": "660688",
      "name": "Keibert Ruiz",
      "team": "WSH",
      "opp_pitcher": "Kyle Bradish",
      "opp_team": "BAL",
      "game": "WSH @ BAL",
      "in_lineup": null,
      "lineup_pos": null,
      "line": "1.5",
      "best_edge": 0.0013303150787699058,
      "p_over_15": 0.5253303150787699,
      "p_over_25": 0.44780928498790534,
      "p_over_15_raw": 0.8077657943398845,
      "p_over_25_raw": 0.5872618729221528,
      "e_hrr": 3.0470221742448196,
      "expected_pa": 4.15,
      "quality_mult": 0.9587075681866775,
      "hf": 1.0,
      "park_mult": 1.05,
      "weather_mult": 1.03881043125,
      "bullpen_mult": 1.0009065988423789,
      "bvp_mult": 1.197183041968038,
      "bvp_pa": 8,
      "bvt_mult": 1.0285557850538245,
      "bvt_pa": 76,
      "bvs_mult": 0.9822789578366352,
      "bvs_pa": 17,
      "impact": 1.0,
      "recent_pa": 34,
      "real_line": 1.5,
      "real_over_price": 125,
      "real_book": "BetMGM",
      "real_p_over": 0.8077657943398845,
      "real_breakeven": 0.4444444444444444,
      "real_edge": 0.36332134989544007
    },
    {
      "rank": 3,
      "batter_id": "668952",
      "name": "Ryan Kreidler",
      "team": "MIN",
      "opp_pitcher": "Ryan Feltner",
      "opp_team": "COL",
      "game": "COL @ MIN",
      "in_lineup": null,
      "lineup_pos": null,
      "line": "1.5",
      "best_edge": -0.0032986112986388427,
      "p_over_15": 0.5207013887013612,
      "p_over_25": 0.44332182814193316,
      "p_over_15_raw": 0.7975311868720389,
      "p_over_25_raw": 0.5718474741990516,
      "e_hrr": 2.9779313318436293,
      "expected_pa": 4.15,
      "quality_mult": 0.9613332489477927,
      "hf": 1.0,
      "park_mult": 1.01,
      "weather_mult": 0.98931793125,
      "bullpen_mult": 1.0314714781530352,
      "bvp_mult": 1.0,
      "bvp_pa": 0,
      "bvt_mult": 1.0134849306221885,
      "bvt_pa": 1,
      "bvs_mult": 1.0101925356821844,
      "bvs_pa": 59,
      "impact": 0.7951482479784368,
      "recent_pa": 31,
      "real_line": 1.5,
      "real_over_price": 129,
      "real_book": "DraftKings",
      "real_p_over": 0.7975311868720389,
      "real_breakeven": 0.4366812227074236,
      "real_edge": 0.36084996416461534
    },
    {
      "rank": 4,
      "batter_id": "622268",
      "name": "Donovan Walton",
      "team": "LAA",
      "opp_pitcher": "Aaron Civale",
      "opp_team": "ATH",
      "game": "ATH @ LAA",
      "in_lineup": null,
      "lineup_pos": null,
      "line": "1.5",
      "best_edge": -0.011499697371673556,
      "p_over_15": 0.5125003026283265,
      "p_over_25": 0.4353334868197874,
      "p_over_15_raw": 0.7784329620419524,
      "p_over_25_raw": 0.5439964444271358,
      "e_hrr": 2.856891674165222,
      "expected_pa": 4.15,
      "quality_mult": 1.1174837884259559,
      "hf": 1.0,
      "park_mult": 0.98,
      "weather_mult": 1.0320343,
      "bullpen_mult": 1.0254122029191668,
      "bvp_mult": 1.0,
      "bvp_pa": 0,
      "bvt_mult": 0.9488597940848273,
      "bvt_pa": 34,
      "bvs_mult": 0.9599114766270646,
      "bvs_pa": 47,
      "impact": 0.6712962962962963,
      "recent_pa": 38,
      "real_line": 1.5,
      "real_over_price": 130,
      "real_book": "BetMGM",
      "real_p_over": 0.7784329620419524,
      "real_breakeven": 0.43478260869565216,
      "real_edge": 0.3436503533463003
    },
    {
      "rank": 5,
      "batter_id": "691720",
      "name": "Kyle Karros",
      "team": "COL",
      "opp_pitcher": "Connor Prielipp",
      "opp_team": "MIN",
      "game": "COL @ MIN",
      "in_lineup": null,
      "lineup_pos": null,
      "line": "1.5",
      "best_edge": -0.02016826215041534,
      "p_over_15": 0.5038317378495847,
      "p_over_25": 0.42683238113868055,
      "p_over_15_raw": 0.756900555009624,
      "p_over_25_raw": 0.5139256773994347,
      "e_hrr": 2.7309466851579662,
      "expected_pa": 4.15,
      "quality_mult": 0.9973621999159674,
      "hf": 1.0300445925810506,
      "park_mult": 1.01,
      "weather_mult": 0.98931793125,
      "bullpen_mult": 1.0351259429181507,
      "bvp_mult": 1.0,
      "bvp_pa": 0,
      "bvt_mult": 1.0739093843815553,
      "bvt_pa": 5,
      "bvs_mult": 1.0500676474842794,
      "bvs_pa": 5,
      "impact": 1.0000000000000002,
      "recent_pa": 33,
      "real_line": 1.5,
      "real_over_price": 140,
      "real_book": "BetMGM",
      "real_p_over": 0.756900555009624,
      "real_breakeven": 0.4166666666666667,
      "real_edge": 0.34023388834295737
    },
    {
      "rank": 6,
      "batter_id": "690993",
      "name": "Colt Keith",
      "team": "DET",
      "opp_pitcher": "Hunter Brown",
      "opp_team": "HOU",
      "game": "HOU @ DET",
      "in_lineup": null,
      "lineup_pos": null,
      "line": "1.5",
      "best_edge": 0.007544922864882397,
      "p_over_15": 0.5315449228648824,
      "p_over_25": 0.453811679385521,
      "p_over_15_raw": 0.8208938348784752,
      "p_over_25_raw": 0.6075665433241315,
      "e_hrr": 3.140622745977556,
      "expected_pa": 4.15,
      "quality_mult": 1.2111872880748504,
      "hf": 1.0,
      "park_mult": 0.98,
      "weather_mult": 1.0475,
      "bullpen_mult": 1.00604271979272,
      "bvp_mult": 1.1253736751517347,
      "bvp_pa": 8,
      "bvt_mult": 1.15,
      "bvt_pa": 51,
      "bvs_mult": 1.048449558603076,
      "bvs_pa": 346,
      "impact": 1.0,
      "recent_pa": 35,
      "real_line": 0.5,
      "real_over_price": -165,
      "real_book": "BetMGM",
      "real_p_over": 0.9567441478952606,
      "real_breakeven": 0.6226415094339622,
      "real_edge": 0.3341026384612984
    },
    {
      "rank": 7,
      "batter_id": "686611",
      "name": "Dylan Crews",
      "team": "WSH",
      "opp_pitcher": "Kyle Bradish",
      "opp_team": "BAL",
      "game": "WSH @ BAL",
      "in_lineup": null,
      "lineup_pos": null,
      "line": "1.5",
      "best_edge": -0.007445879963161373,
      "p_over_15": 0.5165541200368386,
      "p_over_25": 0.43928842501709187,
      "p_over_15_raw": 0.7880279510217949,
      "p_over_25_raw": 0.5578444210516768,
      "e_hrr": 2.9164989999193005,
      "expected_pa": 4.15,
      "quality_mult": 1.0516628244412243,
      "hf": 1.0,
      "park_mult": 1.05,
      "weather_mult": 1.03881043125,
      "bullpen_mult": 1.0009065988423789,
      "bvp_mult": 1.0,
      "bvp_pa": 0,
      "bvt_mult": 1.0342461469912716,
      "bvt_pa": 31,
      "bvs_mult": 1.0233348716641755,
      "bvs_pa": 21,
      "impact": 0.7797179314976495,
      "recent_pa": 58,
      "real_line": 1.5,
      "real_over_price": 120,
      "real_book": "BetMGM",
      "real_p_over": 0.7880279510217949,
      "real_breakeven": 0.45454545454545453,
      "real_edge": 0.3334824964763404
    },
    {
      "rank": 8,
      "batter_id": "673548",
      "name": "Seiya Suzuki",
      "team": "CHC",
      "opp_pitcher": "Brandon Woodruff",
      "opp_team": "MIL",
      "game": "CHC @ MIL",
      "in_lineup": null,
      "lineup_pos": null,
      "line": "1.5",
      "best_edge": -0.029876654705227434,
      "p_over_15": 0.4941233452947726,
      "p_over_25": 0.4172346328548035,
      "p_over_15_raw": 0.7311587504493731,
      "p_over_25_raw": 0.47967988729092936,
      "e_hrr": 2.592475836928711,
      "expected_pa": 4.15,
      "quality_mult": 1.0559905375041547,
      "hf": 0.964236633580284,
      "park_mult": 1.01,
      "weather_mult": 1.0180374125,
      "bullpen_mult": 0.9876544648855863,
      "bvp_mult": 1.1690399930488915,
      "bvp_pa": 13,
      "bvt_mult": 0.9948828249008562,
      "bvt_pa": 207,
      "bvs_mult": 0.9735631863337038,
      "bvs_pa": 36,
      "impact": 1.0,
      "recent_pa": 51,
      "real_line": 1.5,
      "real_over_price": 130,
      "real_book": "DraftKings",
      "real_p_over": 0.7311587504493731,
      "real_breakeven": 0.43478260869565216,
      "real_edge": 0.2963761417537209
    },
    {
      "rank": 9,
      "batter_id": "678391",
      "name": "Jorbit Vivas",
      "team": "WSH",
      "opp_pitcher": "Kyle Bradish",
      "opp_team": "BAL",
      "game": "WSH @ BAL",
      "in_lineup": null,
      "lineup_pos": null,
      "line": "1.5",
      "best_edge": -0.0340566642948717,
      "p_over_15": 0.4899433357051283,
      "p_over_25": 0.4130754461072822,
      "p_over_15_raw": 0.7195565486023769,
      "p_over_25_raw": 0.46481205671443704,
      "e_hrr": 2.5337399634670943,
      "expected_pa": 4.15,
      "quality_mult": 0.9883837436123571,
      "hf": 1.0,
      "park_mult": 1.05,
      "weather_mult": 1.03881043125,
      "bullpen_mult": 1.0009065988423789,
      "bvp_mult": 1.0,
      "bvp_pa": 0,
      "bvt_mult": 1.008828860821218,
      "bvt_pa": 12,
      "bvs_mult": 1.0162876117686344,
      "bvs_pa": 6,
      "impact": 1.0,
      "recent_pa": 24,
      "real_line": 0.5,
      "real_over_price": -167,
      "real_book": "DraftKings",
      "real_p_over": 0.9206383451252964,
      "real_breakeven": 0.6254681647940075,
      "real_edge": 0.29517018033128894
    },
    {
      "rank": 10,
      "batter_id": "605141",
      "name": "Mookie Betts",
      "team": "LAD",
      "opp_pitcher": "Michael King",
      "opp_team": "SD",
      "game": "LAD @ SD",
      "in_lineup": null,
      "lineup_pos": null,
      "line": "1.5",
      "best_edge": 0.0009839667770510374,
      "p_over_15": 0.5249839667770511,
      "p_over_25": 0.4474740274846433,
      "p_over_15_raw": 0.8070135546513508,
      "p_over_25_raw": 0.5861168037024029,
      "e_hrr": 3.041833831591674,
      "expected_pa": 4.15,
      "quality_mult": 1.0541618398475487,
      "hf": 1.0,
      "park_mult": 0.92,
      "weather_mult": 1.013550525,
      "bullpen_mult": 0.9817870049371107,
      "bvp_mult": 1.1163749589293892,
      "bvp_pa": 15,
      "bvt_mult": 1.15,
      "bvt_pa": 390,
      "bvs_mult": 0.9953279036709404,
      "bvs_pa": 49,
      "impact": 1.0,
      "recent_pa": 57,
      "real_line": 1.5,
      "real_over_price": -107,
      "real_book": "DraftKings",
      "real_p_over": 0.8070135546513508,
      "real_breakeven": 0.5169082125603864,
      "real_edge": 0.2901053420909644
    },
    {
      "rank": 11,
      "batter_id": "605137",
      "name": "Josh Bell",
      "team": "MIN",
      "opp_pitcher": "Ryan Feltner",
      "opp_team": "COL",
      "game": "COL @ MIN",
      "in_lineup": null,
      "lineup_pos": null,
      "line": "1.5",
      "best_edge": -0.000137136116634351,
      "p_over_15": 0.5238628638833657,
      "p_over_25": 0.44638827187687724,
      "p_over_15_raw": 0.8045636210319945,
      "p_over_25_raw": 0.5824009510033467,
      "e_hrr": 3.025060262634957,
      "expected_pa": 4.15,
      "quality_mult": 1.0026844468190672,
      "hf": 1.016500629477643,
      "park_mult": 1.01,
      "weather_mult": 0.98931793125,
      "bullpen_mult": 1.0314714781530352,
      "bvp_mult": 1.0228663042003592,
      "bvp_pa": 5,
      "bvt_mult": 1.1307051961352381,
      "bvt_pa": 210,
      "bvs_mult": 0.9942200598903065,
      "bvs_pa": 178,
      "impact": 1.0,
      "recent_pa": 51,
      "real_line": 1.5,
      "real_over_price": -118,
      "real_book": "DraftKings",
      "real_p_over": 0.8045636210319945,
      "real_breakeven": 0.5412844036697247,
      "real_edge": 0.2632792173622698
    },
    {
      "rank": 12,
      "batter_id": "671277",
      "name": "Luis Garc\u00eda Jr.",
      "team": "WSH",
      "opp_pitcher": "Kyle Bradish",
      "opp_team": "BAL",
      "game": "WSH @ BAL",
      "in_lineup": null,
      "lineup_pos": null,
      "line": "1.5",
      "best_edge": -0.0230727291326569,
      "p_over_15": 0.5009272708673431,
      "p_over_25": 0.4239698539376745,
      "p_over_15_raw": 0.7493781180453468,
      "p_over_25_raw": 0.5037327932424959,
      "e_hrr": 2.6892268258978644,
      "expected_pa": 4.15,
      "quality_mult": 1.0383400311758129,
      "hf": 0.9995790729286737,
      "park_mult": 1.05,
      "weather_mult": 1.03881043125,
      "bullpen_mult": 1.0009065988423789,
      "bvp_mult": 0.8856770127510056,
      "bvp_pa": 9,
      "bvt_mult": 0.9,
      "bvt_pa": 89,
      "bvs_mult": 1.058251987695911,
      "bvs_pa": 17,
      "impact": 1.0,
      "recent_pa": 44,
      "real_line": 1.5,
      "real_over_price": -103,
      "real_book": "DraftKings",
      "real_p_over": 0.7493781180453468,
      "real_breakeven": 0.5073891625615764,
      "real_edge": 0.24198895548377042
    },
    {
      "rank": 13,
      "batter_id": "624585",
      "name": "Jorge Soler",
      "team": "LAA",
      "opp_pitcher": "Aaron Civale",
      "opp_team": "ATH",
      "game": "ATH @ LAA",
      "in_lineup": null,
      "lineup_pos": null,
      "line": "1.5",
      "best_edge": -0.017302718821712637,
      "p_over_15": 0.5066972811782874,
      "p_over_25": 0.42964943989927795,
      "p_over_15_raw": 0.7641711570446829,
      "p_over_25_raw": 0.5239284098022026,
      "e_hrr": 2.7723460923601437,
      "expected_pa": 4.15,
      "quality_mult": 1.2385446493326324,
      "hf": 1.0114788546900153,
      "park_mult": 0.98,
      "weather_mult": 1.0320343,
      "bullpen_mult": 1.0254122029191668,
      "bvp_mult": 1.10829930247305,
      "bvp_pa": 8,
      "bvt_mult": 0.9884536914176529,
      "bvt_pa": 127,
      "bvs_mult": 1.0051642610044136,
      "bvs_pa": 254,
      "impact": 0.9370370370370371,
      "recent_pa": 21,
      "real_line": 1.5,
      "real_over_price": -110,
      "real_book": "BetMGM",
      "real_p_over": 0.7641711570446829,
      "real_breakeven": 0.5238095238095238,
      "real_edge": 0.24036163323515902
    },
    {
      "rank": 14,
      "batter_id": "677942",
      "name": "Blaze Alexander",
      "team": "BAL",
      "opp_pitcher": "Zack Littell",
      "opp_team": "WSH",
      "game": "WSH @ BAL",
      "in_lineup": null,
      "lineup_pos": null,
      "line": "1.5",
      "best_edge": -0.03475363546896476,
      "p_over_15": 0.48924636453103526,
      "p_over_25": 0.412380312456417,
      "p_over_15_raw": 0.7175922067805491,
      "p_over_25_raw": 0.46232827895382755,
      "e_hrr": 2.5239998400399966,
      "expected_pa": 4.15,
      "quality_mult": 1.0275105097845108,
      "hf": 1.0,
      "park_mult": 1.05,
      "weather_mult": 1.03881043125,
      "bullpen_mult": 1.0256910978849756,
      "bvp_mult": 1.0194487382403408,
      "bvp_pa": 2,
      "bvt_mult": 0.9426015906016579,
      "bvt_pa": 16,
      "bvs_mult": 1.0215489353160696,
      "bvs_pa": 101,
      "impact": 0.808688387635756,
      "recent_pa": 40,
      "real_line": 1.5,
      "real_over_price": 109,
      "real_book": "DraftKings",
      "real_p_over": 0.7175922067805491,
      "real_breakeven": 0.4784688995215311,
      "real_edge": 0.23912330725901804
    },
    {
      "rank": 15,
      "batter_id": "685133",
      "name": "Wade Meckler",
      "team": "LAA",
      "opp_pitcher": "Aaron Civale",
      "opp_team": "ATH",
      "game": "ATH @ LAA",
      "in_lineup": null,
      "lineup_pos": null,
      "line": "1.5",
      "best_edge": -0.035360725363835666,
      "p_over_15": 0.48863927463616436,
      "p_over_25": 0.41177443702924205,
      "p_over_15_raw": 0.7158743076175565,
      "p_over_25_raw": 0.46016393171508585,
      "e_hrr": 2.515528401470945,
      "expected_pa": 4.15,
      "quality_mult": 1.1581638559204872,
      "hf": 1.0,
      "park_mult": 0.98,
      "weather_mult": 1.0320343,
      "bullpen_mult": 1.0254122029191668,
      "bvp_mult": 0.9877875980147787,
      "bvp_pa": 3,
      "bvt_mult": 1.0228760219786357,
      "bvt_pa": 18,
      "bvs_mult": 1.0680029980570687,
      "bvs_pa": 51,
      "impact": 0.7064814814814815,
      "recent_pa": 45,
      "real_line": 1.5,
      "real_over_price": 107,
      "real_book": "DraftKings",
      "real_p_over": 0.7158743076175565,
      "real_breakeven": 0.4830917874396135,
      "real_edge": 0.23278252017794304
    }
  ]
}